farbox_markdown
