Metadata-Version: 1.0
Name: farbox-markdown
Version: 0.38
Summary: Markdown Compiler for FarBox
Home-page: UNKNOWN
Author: Hepochen
Author-email: hepochen@gmail.com
License: GPL and not allowed for commercial use
Platform: linux
